README.md
pyproject.toml
setup.py
mobilipy/__init__.py
mobilipy/constants.py
mobilipy/gtfs_helper.py
mobilipy/legs.py
mobilipy/mode_detection.py
mobilipy/plot.py
mobilipy/poi_detection.py
mobilipy/preparation.py
mobilipy/privacy.py
mobilipy/reva.py
mobilipy/segmentation.py
mobilipy/waypointsdataframe.py
mobilipy.egg-info/PKG-INFO
mobilipy.egg-info/SOURCES.txt
mobilipy.egg-info/dependency_links.txt
mobilipy.egg-info/top_level.txt