Metadata-Version: 2.1
Name: mobilipy
Version: 0.1.11
Summary: A mobility analysis package developed at the Swiss Data Science Center
Home-page: UNKNOWN
Author: Michal Pleskowicz
Author-email: <michal.pleskowicz@gmail.com>
License: UNKNOWN
Keywords: python,mobility,gps,trips,first package
Platform: UNKNOWN
Classifier: Development Status :: 3 - Alpha
Classifier: Intended Audience :: Education
Classifier: Programming Language :: Python :: 3
Classifier: Operating System :: MacOS :: MacOS X
Classifier: Operating System :: Microsoft :: Windows
